fifa_preprocessing/__init__.py
fifa_preprocessing/fifa_preprocessing.py
fifa_preprocessing-1.1.2.dist-info/LICENSE
fifa_preprocessing-1.1.2.dist-info/METADATA
fifa_preprocessing-1.1.2.dist-info/WHEEL
fifa_preprocessing-1.1.2.dist-info/top_level.txt
fifa_preprocessing-1.1.2.dist-info/RECORD
