Metadata-Version: 2.1
Name: fifa-preprocessing
Version: 1.1.2
Summary: A package providing methods to preprocess data, with the intent to perform Machine Learning.
Home-page: https://github.com/piotrfratczak/fifa_preprocessing/
Author: Piotr Frątczak
Author-email: piotrfratczak99@gmail.com
License: UNKNOWN
Platform: UNKNOWN
Classifier: Programming Language :: Python :: 3
Classifier: Development Status :: 3 - Alpha
Classifier: License :: OSI Approved :: MIT License
Classifier: Operating System :: OS Independent
Requires-Python: >=3.6
